{
  "pins": {
    "PIN1": {
      "PIN": "RE5",
      "PMD": "PMD5",
      "PPS": {
        "name": "RPE5",
        "ppsgroup": 2,
        "ppsval": 6
      },
      "PinFunctions": {
        "direction": {
          "in": [
            "INT4",
            "T5CK",
            "T7CK",
            "IC4",
            "IC8",
            "U3RX",
            "U4CTS",
            "SDI2",
            "SDI4",
            "C1RX",
            "REFCLKI4",
            "ETXEN",
            "AN17"
          ],
          "out": [
            "U1TX",
            "U2RTS",
            "U5TX",
            "U6RTS",
            "SDO1",
            "SDO2",
            "SDO3",
            "SDO4",
            "OC4",
            "OC7",
            "REFCLKO1"
          ]
        }
      }
    },
    "PIN2": {
      "PIN": "RE6",
      "PMD": "PMD6",
      "PPS": null,
      "PinFunctions": {
        "direction": {
          "in": [
            "ETXD0",
            "AN16"
          ]
        }
      }
    },
    "PIN3": {
      "PIN": "RE7",
      "PMD": "PMD7",
      "PPS": null,
      "PinFunctions": {
        "direction": {
          "in": [
            "ETXD1",
            "AN15"
          ]
        }
      }
    },
    "PIN4": {
      "PIN": "RG6",
      "PMD": null,
      "PPS": {
        "name": "RPG6",
        "ppsgroup": 3,
        "ppsval": 1
      },
      "PinFunctions": {
        "direction": {
          "in": [
            "INT2",
            "T3CK",
            "T8CK",
            "IC2",
            "IC5",
            "IC9",
            "U1CTS",
            "U2RX",
            "U5CTS",
            "SS1",
            "SS3",
            "SS4",
            "C2RX",
            "PMA5",
            "SCK2",
            "C1IND",
            "AN14"
          ],
          "out": [
            "U3RTS",
            "U4TX",
            "U6TX",
            "SS1",
            "SS3",
            "SS4",
            "OC5",
            "OC8",
            "C1OUT",
            "REFCLKO3"
          ]
        }
      }
    },
    "PIN5": {
      "PIN": "RG7",
      "PMD": null,
      "PPS": {
        "name": "RPG7",
        "ppsgroup": 2,
        "ppsval": 1
      },
      "PinFunctions": {
        "direction": {
          "in": [
            "INT4",
            "T5CK",
            "T7CK",
            "IC4",
            "IC8",
            "U3RX",
            "U4CTS",
            "SDI2",
            "SDI4",
            "C1RX",
            "REFCLKI4",
            "PMA4",
            "SDA4",
            "C1INC",
            "AN13"
          ],
          "out": [
            "U1TX",
            "U2RTS",
            "U5TX",
            "U6RTS",
            "SDO1",
            "SDO2",
            "SDO3",
            "SDO4",
            "OC4",
            "OC7",
            "REFCLKO1"
          ]
        }
      }
    },
    "PIN6": {
      "PIN": "RG8",
      "PMD": null,
      "PPS": {
        "name": "RPG8",
        "ppsgroup": 1,
        "ppsval": 1
      },
      "PinFunctions": {
        "direction": {
          "in": [
            "INT3",
            "T2CK",
            "T6CK",
            "IC3",
            "IC7",
            "U1RX",
            "U2CTS",
            "U5RX",
            "U6CTS",
            "SDI1",
            "SDI3",
            "REFCLKI1",
            "PMA3",
            "SCL4",
            "C2IND",
            "AN12"
          ],
          "out": [
            "U3TX",
            "U4RTS",
            "SDO1",
            "SDO2",
            "SDO3",
            "OC3",
            "OC6",
            "REFCLKO4",
            "C2OUT",
            "C1TX"
          ]
        }
      }
    },
    "PIN7": {
      "PIN": "VSS",
      "PMD": null,
      "PPS": null,
      "PinFunctions": {
        "direction": {}
      }
    },
    "PIN8": {
      "PIN": "VDD",
      "PMD": null,
      "PPS": null,
      "PinFunctions": {
        "direction": {}
      }
    },
    "PIN9": {
      "PIN": "MCLR",
      "PMD": null,
      "PPS": null,
      "PinFunctions": {
        "direction": {}
      }
    },
    "PIN10": {
      "PIN": "RG9",
      "PMD": null,
      "PPS": {
        "name": "RPG9",
        "ppsgroup": 4,
        "ppsval": 1
      },
      "PinFunctions": {
        "direction": {
          "in": [
            "INT1",
            "T4CK",
            "T9CK",
            "IC1",
            "IC6",
            "U3CTS",
            "U4RX",
            "U6RX",
            "SS2",
            "OCFA",
            "REFCLKI3",
            "PMA2",
            "C2INC",
            "AN11"
          ],
          "out": [
            "U1RTS",
            "U2TX",
            "U5RTS",
            "U6TX",
            "SS2",
            "SDO4",
            "OC2",
            "OC1",
            "OC9",
            "C2TX"
          ]
        }
      }
    },
    "PIN11": {
      "PIN": "RB5",
      "PMD": null,
      "PPS": {
        "name": "RPB5",
        "ppsgroup": 1,
        "ppsval": 8
      },
      "PinFunctions": {
        "direction": {
          "in": [
            "INT3",
            "T2CK",
            "T6CK",
            "IC3",
            "IC7",
            "U1RX",
            "U2CTS",
            "U5RX",
            "U6CTS",
            "SDI1",
            "SDI3",
            "REFCLKI1",
            "C1INA",
            "AN45"
          ],
          "out": [
            "U3TX",
            "U4RTS",
            "SDO1",
            "SDO2",
            "SDO3",
            "OC3",
            "OC6",
            "REFCLKO4",
            "C2OUT",
            "C1TX"
          ]
        }
      }
    },
    "PIN12": {
      "PIN": "RB4",
      "PMD": null,
      "PPS": null,
      "PinFunctions": {
        "direction": {
          "in": [
            "C1INB",
            "AN4"
          ]
        }
      }
    },
    "PIN13": {
      "PIN": "RB3",
      "PMD": null,
      "PPS": {
        "name": "RPB3",
        "ppsgroup": 2,
        "ppsval": 8
      },
      "PinFunctions": {
        "direction": {
          "in": [
            "INT4",
            "T5CK",
            "T7CK",
            "IC4",
            "IC8",
            "U3RX",
            "U4CTS",
            "SDI2",
            "SDI4",
            "C1RX",
            "REFCLKI4",
            "C2INA",
            "AN3"
          ],
          "out": [
            "U1TX",
            "U2RTS",
            "U5TX",
            "U6RTS",
            "SDO1",
            "SDO2",
            "SDO3",
            "SDO4",
            "OC4",
            "OC7",
            "REFCLKO1"
          ]
        }
      }
    },
    "PIN14": {
      "PIN": "RB2",
      "PMD": null,
      "PPS": {
        "name": "RPB2",
        "ppsgroup": 4,
        "ppsval": 7
      },
      "PinFunctions": {
        "direction": {
          "in": [
            "INT1",
            "T4CK",
            "T9CK",
            "IC1",
            "IC6",
            "U3CTS",
            "U4RX",
            "U6RX",
            "SS2",
            "OCFA",
            "REFCLKI3",
            "C2INB",
            "AN2"
          ],
          "out": [
            "U1RTS",
            "U2TX",
            "U5RTS",
            "U6TX",
            "SS2",
            "SDO4",
            "OC2",
            "OC1",
            "OC9",
            "C2TX"
          ]
        }
      }
    },
    "PIN15": {
      "PIN": "RB1",
      "PMD": null,
      "PPS": {
        "name": "RPB1",
        "ppsgroup": 2,
        "ppsval": 5
      },
      "PinFunctions": {
        "direction": {
          "in": [
            "INT4",
            "T5CK",
            "T7CK",
            "IC4",
            "IC8",
            "U3RX",
            "U4CTS",
            "SDI2",
            "SDI4",
            "C1RX",
            "REFCLKI4",
            "AN1",
            "VREF-",
            "PGEC1"
          ],
          "out": [
            "U1TX",
            "U2RTS",
            "U5TX",
            "U6RTS",
            "SDO1",
            "SDO2",
            "SDO3",
            "SDO4",
            "OC4",
            "OC7",
            "REFCLKO1"
          ]
        }
      }
    },
    "PIN16": {
      "PIN": "RB0",
      "PMD": null,
      "PPS": {
        "name": "RPB0",
        "ppsgroup": 3,
        "ppsval": 5
      },
      "PinFunctions": {
        "direction": {
          "in": [
            "INT2",
            "T3CK",
            "T8CK",
            "IC2",
            "IC5",
            "IC9",
            "U1CTS",
            "U2RX",
            "U5CTS",
            "SS1",
            "SS3",
            "SS4",
            "C2RX",
            "PMA6",
            "AN0",
            "VREF\u002B",
            "PGED1"
          ],
          "out": [
            "U3RTS",
            "U4TX",
            "U6TX",
            "SS1",
            "SS3",
            "SS4",
            "OC5",
            "OC8",
            "C1OUT",
            "REFCLKO3"
          ]
        }
      }
    },
    "PIN17": {
      "PIN": "RB6",
      "PMD": null,
      "PPS": {
        "name": "RPB6",
        "ppsgroup": 4,
        "ppsval": 5
      },
      "PinFunctions": {
        "direction": {
          "in": [
            "INT1",
            "T4CK",
            "T9CK",
            "IC1",
            "IC6",
            "U3CTS",
            "U4RX",
            "U6RX",
            "SS2",
            "OCFA",
            "REFCLKI3",
            "AN46",
            "PGEC2"
          ],
          "out": [
            "U1RTS",
            "U2TX",
            "U5RTS",
            "U6TX",
            "SS2",
            "SDO4",
            "OC2",
            "OC1",
            "OC9",
            "C2TX"
          ]
        }
      }
    },
    "PIN18": {
      "PIN": "RB7",
      "PMD": null,
      "PPS": {
        "name": "RPB7",
        "ppsgroup": 3,
        "ppsval": 7
      },
      "PinFunctions": {
        "direction": {
          "in": [
            "INT2",
            "T3CK",
            "T8CK",
            "IC2",
            "IC5",
            "IC9",
            "U1CTS",
            "U2RX",
            "U5CTS",
            "SS1",
            "SS3",
            "SS4",
            "C2RX",
            "AN47",
            "PGED2"
          ],
          "out": [
            "U3RTS",
            "U4TX",
            "U6TX",
            "SS1",
            "SS3",
            "SS4",
            "OC5",
            "OC8",
            "C1OUT",
            "REFCLKO3"
          ]
        }
      }
    },
    "PIN19": {
      "PIN": "AVDD",
      "PMD": null,
      "PPS": null,
      "PinFunctions": {
        "direction": {}
      }
    },
    "PIN20": {
      "PIN": "AVSS",
      "PMD": null,
      "PPS": null,
      "PinFunctions": {
        "direction": {}
      }
    },
    "PIN21": {
      "PIN": "RB8",
      "PMD": null,
      "PPS": {
        "name": "RPB8",
        "ppsgroup": 3,
        "ppsval": 2
      },
      "PinFunctions": {
        "direction": {
          "in": [
            "INT2",
            "T3CK",
            "T8CK",
            "IC2",
            "IC5",
            "IC9",
            "U1CTS",
            "U2RX",
            "U5CTS",
            "SS1",
            "SS3",
            "SS4",
            "C2RX",
            "PMA10",
            "AN48"
          ],
          "out": [
            "U3RTS",
            "U4TX",
            "U6TX",
            "SS1",
            "SS3",
            "SS4",
            "OC5",
            "OC8",
            "C1OUT",
            "REFCLKO3"
          ]
        }
      }
    },
    "PIN22": {
      "PIN": "RB9",
      "PMD": null,
      "PPS": {
        "name": "RPB9",
        "ppsgroup": 1,
        "ppsval": 5
      },
      "PinFunctions": {
        "direction": {
          "in": [
            "INT3",
            "T2CK",
            "T6CK",
            "IC3",
            "IC7",
            "U1RX",
            "U2CTS",
            "U5RX",
            "U6CTS",
            "SDI1",
            "SDI3",
            "REFCLKI1",
            "PMA7",
            "AN49"
          ],
          "out": [
            "U3TX",
            "U4RTS",
            "SDO1",
            "SDO2",
            "SDO3",
            "OC3",
            "OC6",
            "REFCLKO4",
            "C2OUT",
            "C1TX"
          ]
        }
      }
    },
    "PIN23": {
      "PIN": "RB10",
      "PMD": null,
      "PPS": {
        "name": "RPB10",
        "ppsgroup": 1,
        "ppsval": 6
      },
      "PinFunctions": {
        "direction": {
          "in": [
            "INT3",
            "T2CK",
            "T6CK",
            "IC3",
            "IC7",
            "U1RX",
            "U2CTS",
            "U5RX",
            "U6CTS",
            "SDI1",
            "SDI3",
            "REFCLKI1",
            "PMA13",
            "AN5",
            "CVREFOUT",
            "TMS"
          ],
          "out": [
            "U3TX",
            "U4RTS",
            "SDO1",
            "SDO2",
            "SDO3",
            "OC3",
            "OC6",
            "REFCLKO4",
            "C2OUT",
            "C1TX"
          ]
        }
      }
    },
    "PIN24": {
      "PIN": "RB11",
      "PMD": null,
      "PPS": null,
      "PinFunctions": {
        "direction": {
          "in": [
            "PMA12",
            "AN6",
            "TDO"
          ]
        }
      }
    },
    "PIN25": {
      "PIN": "VSS",
      "PMD": null,
      "PPS": null,
      "PinFunctions": {
        "direction": {}
      }
    },
    "PIN26": {
      "PIN": "VDD",
      "PMD": null,
      "PPS": null,
      "PinFunctions": {
        "direction": {}
      }
    },
    "PIN27": {
      "PIN": "RB12",
      "PMD": null,
      "PPS": null,
      "PinFunctions": {
        "direction": {
          "in": [
            "PMA11",
            "AN7",
            "TCK"
          ]
        }
      }
    },
    "PIN28": {
      "PIN": "RB13",
      "PMD": null,
      "PPS": null,
      "PinFunctions": {
        "direction": {
          "in": [
            "AN8",
            "TDI"
          ]
        }
      }
    },
    "PIN29": {
      "PIN": "RB14",
      "PMD": null,
      "PPS": {
        "name": "RPB14",
        "ppsgroup": 4,
        "ppsval": 2
      },
      "PinFunctions": {
        "direction": {
          "in": [
            "INT1",
            "T4CK",
            "T9CK",
            "IC1",
            "IC6",
            "U3CTS",
            "U4RX",
            "U6RX",
            "SS2",
            "OCFA",
            "REFCLKI3",
            "PMA1",
            "SCK3",
            "AN9"
          ],
          "out": [
            "U1RTS",
            "U2TX",
            "U5RTS",
            "U6TX",
            "SS2",
            "SDO4",
            "OC2",
            "OC1",
            "OC9",
            "C2TX"
          ]
        }
      }
    },
    "PIN30": {
      "PIN": "RB15",
      "PMD": null,
      "PPS": {
        "name": "RPB15",
        "ppsgroup": 3,
        "ppsval": 3
      },
      "PinFunctions": {
        "direction": {
          "in": [
            "INT2",
            "T3CK",
            "T8CK",
            "IC2",
            "IC5",
            "IC9",
            "U1CTS",
            "U2RX",
            "U5CTS",
            "SS1",
            "SS3",
            "SS4",
            "C2RX",
            "PMA0",
            "OCFB",
            "AEMDC",
            "EMDC",
            "AN10"
          ],
          "out": [
            "U3RTS",
            "U4TX",
            "U6TX",
            "SS1",
            "SS3",
            "SS4",
            "OC5",
            "OC8",
            "C1OUT",
            "REFCLKO3"
          ]
        }
      }
    },
    "PIN31": {
      "PIN": "RC12",
      "PMD": null,
      "PPS": null,
      "PinFunctions": {
        "direction": {
          "in": [
            "CLKI",
            "OSC1"
          ]
        }
      }
    },
    "PIN32": {
      "PIN": "RC15",
      "PMD": null,
      "PPS": null,
      "PinFunctions": {
        "direction": {
          "in": [
            "CLKO",
            "OSC2"
          ]
        }
      }
    },
    "PIN33": {
      "PIN": "VBUS",
      "PMD": null,
      "PPS": null,
      "PinFunctions": {
        "direction": {}
      }
    },
    "PIN34": {
      "PIN": "VUSB3V3",
      "PMD": null,
      "PPS": null,
      "PinFunctions": {
        "direction": {}
      }
    },
    "PIN35": {
      "PIN": "VSS",
      "PMD": null,
      "PPS": null,
      "PinFunctions": {
        "direction": {}
      }
    },
    "PIN36": {
      "PIN": "D-",
      "PMD": null,
      "PPS": null,
      "PinFunctions": {
        "direction": {}
      }
    },
    "PIN37": {
      "PIN": "D\u002B",
      "PMD": null,
      "PPS": null,
      "PinFunctions": {
        "direction": {}
      }
    },
    "PIN38": {
      "PIN": "RF3",
      "PMD": null,
      "PPS": {
        "name": "RPF3",
        "ppsgroup": 4,
        "ppsval": 8
      },
      "PinFunctions": {
        "direction": {
          "in": [
            "INT1",
            "T4CK",
            "T9CK",
            "IC1",
            "IC6",
            "U3CTS",
            "U4RX",
            "U6RX",
            "SS2",
            "OCFA",
            "REFCLKI3",
            "USBID"
          ],
          "out": [
            "U1RTS",
            "U2TX",
            "U5RTS",
            "U6TX",
            "SS2",
            "SDO4",
            "OC2",
            "OC1",
            "OC9",
            "C2TX"
          ]
        }
      }
    },
    "PIN39": {
      "PIN": "VDD",
      "PMD": null,
      "PPS": null,
      "PinFunctions": {
        "direction": {}
      }
    },
    "PIN40": {
      "PIN": "VSS",
      "PMD": null,
      "PPS": null,
      "PinFunctions": {
        "direction": {}
      }
    },
    "PIN41": {
      "PIN": "RF4",
      "PMD": null,
      "PPS": {
        "name": "RPF4",
        "ppsgroup": 1,
        "ppsval": 2
      },
      "PinFunctions": {
        "direction": {
          "in": [
            "INT3",
            "T2CK",
            "T6CK",
            "IC3",
            "IC7",
            "U1RX",
            "U2CTS",
            "U5RX",
            "U6CTS",
            "SDI1",
            "SDI3",
            "REFCLKI1",
            "PMA9",
            "SDA5"
          ],
          "out": [
            "U3TX",
            "U4RTS",
            "SDO1",
            "SDO2",
            "SDO3",
            "OC3",
            "OC6",
            "REFCLKO4",
            "C2OUT",
            "C1TX"
          ]
        }
      }
    },
    "PIN42": {
      "PIN": "RF5",
      "PMD": null,
      "PPS": {
        "name": "RPF5",
        "ppsgroup": 2,
        "ppsval": 2
      },
      "PinFunctions": {
        "direction": {
          "in": [
            "INT4",
            "T5CK",
            "T7CK",
            "IC4",
            "IC8",
            "U3RX",
            "U4CTS",
            "SDI2",
            "SDI4",
            "C1RX",
            "REFCLKI4",
            "PMA8",
            "SCL5"
          ],
          "out": [
            "U1TX",
            "U2RTS",
            "U5TX",
            "U6RTS",
            "SDO1",
            "SDO2",
            "SDO3",
            "SDO4",
            "OC4",
            "OC7",
            "REFCLKO1"
          ]
        }
      }
    },
    "PIN43": {
      "PIN": "RD9",
      "PMD": null,
      "PPS": {
        "name": "RPD9",
        "ppsgroup": 3,
        "ppsval": 0
      },
      "PinFunctions": {
        "direction": {
          "in": [
            "INT2",
            "T3CK",
            "T8CK",
            "IC2",
            "IC5",
            "IC9",
            "U1CTS",
            "U2RX",
            "U5CTS",
            "SS1",
            "SS3",
            "SS4",
            "C2RX",
            "PMA15",
            "PMCS2",
            "SDA1",
            "ETXD2",
            "AERXD0"
          ],
          "out": [
            "U3RTS",
            "U4TX",
            "U6TX",
            "SS1",
            "SS3",
            "SS4",
            "OC5",
            "OC8",
            "C1OUT",
            "REFCLKO3"
          ]
        }
      }
    },
    "PIN44": {
      "PIN": "RD10",
      "PMD": null,
      "PPS": {
        "name": "RPD10",
        "ppsgroup": 1,
        "ppsval": 3
      },
      "PinFunctions": {
        "direction": {
          "in": [
            "INT3",
            "T2CK",
            "T6CK",
            "IC3",
            "IC7",
            "U1RX",
            "U2CTS",
            "U5RX",
            "U6CTS",
            "SDI1",
            "SDI3",
            "REFCLKI1",
            "SCK4",
            "SCL1",
            "ECOL"
          ],
          "out": [
            "U3TX",
            "U4RTS",
            "SDO1",
            "SDO2",
            "SDO3",
            "OC3",
            "OC6",
            "REFCLKO4",
            "C2OUT",
            "C1TX"
          ]
        }
      }
    },
    "PIN45": {
      "PIN": "RD11",
      "PMD": null,
      "PPS": {
        "name": "RPD11",
        "ppsgroup": 2,
        "ppsval": 3
      },
      "PinFunctions": {
        "direction": {
          "in": [
            "INT4",
            "T5CK",
            "T7CK",
            "IC4",
            "IC8",
            "U3RX",
            "U4CTS",
            "SDI2",
            "SDI4",
            "C1RX",
            "REFCLKI4",
            "PMA14",
            "PMCS1",
            "ECRS",
            "AEREFCLK",
            "AERXCLK"
          ],
          "out": [
            "U1TX",
            "U2RTS",
            "U5TX",
            "U6RTS",
            "SDO1",
            "SDO2",
            "SDO3",
            "SDO4",
            "OC4",
            "OC7",
            "REFCLKO1"
          ]
        }
      }
    },
    "PIN46": {
      "PIN": "RD0",
      "PMD": null,
      "PPS": {
        "name": "RPD0",
        "ppsgroup": 4,
        "ppsval": 3
      },
      "PinFunctions": {
        "direction": {
          "in": [
            "INT1",
            "T4CK",
            "T9CK",
            "IC1",
            "IC6",
            "U3CTS",
            "U4RX",
            "U6RX",
            "SS2",
            "OCFA",
            "REFCLKI3",
            "INT0",
            "RTCC",
            "ETXD3",
            "AERXD1"
          ],
          "out": [
            "U1RTS",
            "U2TX",
            "U5RTS",
            "U6TX",
            "SS2",
            "SDO4",
            "OC2",
            "OC1",
            "OC9",
            "C2TX"
          ]
        }
      }
    },
    "PIN47": {
      "PIN": "RC13",
      "PMD": null,
      "PPS": {
        "name": "RPC13",
        "ppsgroup": 2,
        "ppsval": 7
      },
      "PinFunctions": {
        "direction": {
          "in": [
            "INT4",
            "T5CK",
            "T7CK",
            "IC4",
            "IC8",
            "U3RX",
            "U4CTS",
            "SDI2",
            "SDI4",
            "C1RX",
            "REFCLKI4",
            "SOSCI"
          ],
          "out": [
            "U1TX",
            "U2RTS",
            "U5TX",
            "U6RTS",
            "SDO1",
            "SDO2",
            "SDO3",
            "SDO4",
            "OC4",
            "OC7",
            "REFCLKO1"
          ]
        }
      }
    },
    "PIN48": {
      "PIN": "RC14",
      "PMD": null,
      "PPS": {
        "name": "RPC14",
        "ppsgroup": 1,
        "ppsval": 7
      },
      "PinFunctions": {
        "direction": {
          "in": [
            "INT3",
            "T2CK",
            "T6CK",
            "IC3",
            "IC7",
            "U1RX",
            "U2CTS",
            "U5RX",
            "U6CTS",
            "SDI1",
            "SDI3",
            "REFCLKI1",
            "T1CK",
            "SOSCO"
          ],
          "out": [
            "U3TX",
            "U4RTS",
            "SDO1",
            "SDO2",
            "SDO3",
            "OC3",
            "OC6",
            "REFCLKO4",
            "C2OUT",
            "C1TX"
          ]
        }
      }
    },
    "PIN49": {
      "PIN": "RD1",
      "PMD": null,
      "PPS": {
        "name": "RPD1",
        "ppsgroup": 4,
        "ppsval": 0
      },
      "PinFunctions": {
        "direction": {
          "in": [
            "INT1",
            "T4CK",
            "T9CK",
            "IC1",
            "IC6",
            "U3CTS",
            "U4RX",
            "U6RX",
            "SS2",
            "OCFA",
            "REFCLKI3",
            "SCK1",
            "AEMDIO",
            "EMDIO"
          ],
          "out": [
            "U1RTS",
            "U2TX",
            "U5RTS",
            "U6TX",
            "SS2",
            "SDO4",
            "OC2",
            "OC1",
            "OC9",
            "C2TX"
          ]
        }
      }
    },
    "PIN50": {
      "PIN": "RD2",
      "PMD": null,
      "PPS": {
        "name": "RPD2",
        "ppsgroup": 1,
        "ppsval": 0
      },
      "PinFunctions": {
        "direction": {
          "in": [
            "INT3",
            "T2CK",
            "T6CK",
            "IC3",
            "IC7",
            "U1RX",
            "U2CTS",
            "U5RX",
            "U6CTS",
            "SDI1",
            "SDI3",
            "REFCLKI1",
            "SDA3",
            "AETXEN",
            "ETXERR"
          ],
          "out": [
            "U3TX",
            "U4RTS",
            "SDO1",
            "SDO2",
            "SDO3",
            "OC3",
            "OC6",
            "REFCLKO4",
            "C2OUT",
            "C1TX"
          ]
        }
      }
    },
    "PIN51": {
      "PIN": "RD3",
      "PMD": null,
      "PPS": {
        "name": "RPD3",
        "ppsgroup": 2,
        "ppsval": 0
      },
      "PinFunctions": {
        "direction": {
          "in": [
            "INT4",
            "T5CK",
            "T7CK",
            "IC4",
            "IC8",
            "U3RX",
            "U4CTS",
            "SDI2",
            "SDI4",
            "C1RX",
            "REFCLKI4",
            "SCL3",
            "ETXCLK",
            "AERXERR"
          ],
          "out": [
            "U1TX",
            "U2RTS",
            "U5TX",
            "U6RTS",
            "SDO1",
            "SDO2",
            "SDO3",
            "SDO4",
            "OC4",
            "OC7",
            "REFCLKO1"
          ]
        }
      }
    },
    "PIN52": {
      "PIN": "RD4",
      "PMD": null,
      "PPS": {
        "name": "RPD4",
        "ppsgroup": 3,
        "ppsval": 4
      },
      "PinFunctions": {
        "direction": {
          "in": [
            "INT2",
            "T3CK",
            "T8CK",
            "IC2",
            "IC5",
            "IC9",
            "U1CTS",
            "U2RX",
            "U5CTS",
            "SS1",
            "SS3",
            "SS4",
            "C2RX",
            "PMWR",
            "SQICS0"
          ],
          "out": [
            "U3RTS",
            "U4TX",
            "U6TX",
            "SS1",
            "SS3",
            "SS4",
            "OC5",
            "OC8",
            "C1OUT",
            "REFCLKO3"
          ]
        }
      }
    },
    "PIN53": {
      "PIN": "RD5",
      "PMD": null,
      "PPS": {
        "name": "RPD5",
        "ppsgroup": 4,
        "ppsval": 6
      },
      "PinFunctions": {
        "direction": {
          "in": [
            "INT1",
            "T4CK",
            "T9CK",
            "IC1",
            "IC6",
            "U3CTS",
            "U4RX",
            "U6RX",
            "SS2",
            "OCFA",
            "REFCLKI3",
            "PMRD",
            "SQICS1"
          ],
          "out": [
            "U1RTS",
            "U2TX",
            "U5RTS",
            "U6TX",
            "SS2",
            "SDO4",
            "OC2",
            "OC1",
            "OC9",
            "C2TX"
          ]
        }
      }
    },
    "PIN54": {
      "PIN": "VDD",
      "PMD": null,
      "PPS": null,
      "PinFunctions": {
        "direction": {}
      }
    },
    "PIN55": {
      "PIN": "VSS",
      "PMD": null,
      "PPS": null,
      "PinFunctions": {
        "direction": {}
      }
    },
    "PIN56": {
      "PIN": "RF0",
      "PMD": null,
      "PPS": {
        "name": "RPF0",
        "ppsgroup": 2,
        "ppsval": 4
      },
      "PinFunctions": {
        "direction": {
          "in": [
            "INT4",
            "T5CK",
            "T7CK",
            "IC4",
            "IC8",
            "U3RX",
            "U4CTS",
            "SDI2",
            "SDI4",
            "C1RX",
            "REFCLKI4",
            "AETXD1",
            "ERXD3"
          ],
          "out": [
            "U1TX",
            "U2RTS",
            "U5TX",
            "U6RTS",
            "SDO1",
            "SDO2",
            "SDO3",
            "SDO4",
            "OC4",
            "OC7",
            "REFCLKO1"
          ]
        }
      }
    },
    "PIN57": {
      "PIN": "RF1",
      "PMD": null,
      "PPS": {
        "name": "RPF1",
        "ppsgroup": 1,
        "ppsval": 4
      },
      "PinFunctions": {
        "direction": {
          "in": [
            "INT3",
            "T2CK",
            "T6CK",
            "IC3",
            "IC7",
            "U1RX",
            "U2CTS",
            "U5RX",
            "U6CTS",
            "SDI1",
            "SDI3",
            "REFCLKI1",
            "AETXD0",
            "ERXD2",
            "SQICLK",
            "TRCLK"
          ],
          "out": [
            "U3TX",
            "U4RTS",
            "SDO1",
            "SDO2",
            "SDO3",
            "OC3",
            "OC6",
            "REFCLKO4",
            "C2OUT",
            "C1TX"
          ]
        }
      }
    },
    "PIN58": {
      "PIN": "RE0",
      "PMD": "PMD0",
      "PPS": null,
      "PinFunctions": {
        "direction": {
          "in": [
            "ERXD1",
            "SQID0",
            "TRD0"
          ]
        }
      }
    },
    "PIN59": {
      "PIN": "VSS",
      "PMD": null,
      "PPS": null,
      "PinFunctions": {
        "direction": {}
      }
    },
    "PIN60": {
      "PIN": "VDD",
      "PMD": null,
      "PPS": null,
      "PinFunctions": {
        "direction": {}
      }
    },
    "PIN61": {
      "PIN": "RE1",
      "PMD": "PMD1",
      "PPS": null,
      "PinFunctions": {
        "direction": {
          "in": [
            "ERXD0",
            "SQID1",
            "TRD1"
          ]
        }
      }
    },
    "PIN62": {
      "PIN": "RE2",
      "PMD": "PMD2",
      "PPS": null,
      "PinFunctions": {
        "direction": {
          "in": [
            "AECRSDV",
            "ECRSDV",
            "ERXDV",
            "SQID2",
            "TRD2"
          ]
        }
      }
    },
    "PIN63": {
      "PIN": "RE3",
      "PMD": "PMD3",
      "PPS": {
        "name": "RPE3",
        "ppsgroup": 3,
        "ppsval": 6
      },
      "PinFunctions": {
        "direction": {
          "in": [
            "INT2",
            "T3CK",
            "T8CK",
            "IC2",
            "IC5",
            "IC9",
            "U1CTS",
            "U2RX",
            "U5CTS",
            "SS1",
            "SS3",
            "SS4",
            "C2RX",
            "EREFCLK",
            "ERXCLK",
            "SQID3",
            "TRD3"
          ],
          "out": [
            "U3RTS",
            "U4TX",
            "U6TX",
            "SS1",
            "SS3",
            "SS4",
            "OC5",
            "OC8",
            "C1OUT",
            "REFCLKO3"
          ]
        }
      }
    },
    "PIN64": {
      "PIN": "RE4",
      "PMD": "PMD4",
      "PPS": null,
      "PinFunctions": {
        "direction": {
          "in": [
            "ERXERR",
            "AN18"
          ]
        }
      }
    }
  }
}